Metadata-Version: 1.0
Name: pol-gnb-probability
Version: 0.1
Summary: Gaussian distributions & Binomial distribution
Home-page: UNKNOWN
Author: Panjapol Ampornratana
Author-email: panjapol.pol@gmail.com
License: UNKNOWN
Platform: UNKNOWN
